yta_web_scraper/__init__.py
yta_web_scraper/chrome.py
yta_web_scraper-0.0.6.dist-info/licenses/LICENSE
yta_web_scraper-0.0.6.dist-info/METADATA
yta_web_scraper-0.0.6.dist-info/WHEEL
yta_web_scraper-0.0.6.dist-info/RECORD
