Metadata-Version: 2.4
Name: yta-web-scraper
Version: 0.0.6
Summary: Youtube Autonomous Chrome Scraper Module
License-File: LICENSE
Author: danialcala94
Author-email: danielalcalavalera@gmail.com
Requires-Python: ==3.9
Classifier: Programming Language :: Python :: 3
Classifier: Programming Language :: Python :: 3.9
Requires-Dist: selenium (>=4.18.1,<5.0.0)
Requires-Dist: yta_constants (>=0.0.1,<1.0.0)
Requires-Dist: yta_file (>=0.0.1,<1.0.0)
Requires-Dist: yta_validation (>=0.0.1,<1.0.0)
